simple_bcp/__init__.py
simple_bcp/_bcp.py
simple_bcp/_connection_parameters.py
simple_bcp/_encoding.py
simple_bcp/_options.py
simple_bcp-2.2.1.dist-info/LICENSE
simple_bcp-2.2.1.dist-info/METADATA
simple_bcp-2.2.1.dist-info/WHEEL
simple_bcp-2.2.1.dist-info/RECORD
