Metadata-Version: 2.3
Name: simple_bcp
Version: 2.2.1
Summary: A Simple yet powerful bcp wrapper
License: MIT
Author: Noam Fisher
Author-email: noam9997@gmail.com
Requires-Python: >=3.10,<4.0
Classifier: License :: OSI Approved :: MIT License
Classifier: Operating System :: OS Independent
Classifier: Programming Language :: Python :: 3
Classifier: Programming Language :: Python :: 3.10
Classifier: Programming Language :: Python :: 3.11
Classifier: Programming Language :: Python :: 3.12
Classifier: Programming Language :: Python :: 3.13
Requires-Dist: annotated-types (>=0.7.0,<0.8.0)
Requires-Dist: packaging (>=25.0,<26.0)
Requires-Dist: pydantic (>=2.11,<3.0)
Project-URL: Homepage, https://gitlab.com/noamfisher/simple_bcp
Project-URL: changelog, https://gitlab.com/noamfisher/simple_bcp/-/blob/main/CHANGELOG.md
